parsegitlog/__init__.py
parsegitlog/__main__.py
parsegitlog/gitlog.py
parsegitlog/test_gitlog.py
parsegitlog-0.0.3.dist-info/METADATA
parsegitlog-0.0.3.dist-info/WHEEL
parsegitlog-0.0.3.dist-info/top_level.txt
parsegitlog-0.0.3.dist-info/RECORD
