Metadata-Version: 2.1
Name: parsegitlog
Version: 0.0.3
Summary: Get a representation of commits in a git repository as JSON
Home-page: https://github.com/zgulde/parsegitlog
Author: Zach Gulde
Author-email: zachgulde@gmail.com
License: UNKNOWN
Platform: UNKNOWN
Classifier: Programming Language :: Python :: 3
Classifier: License :: OSI Approved :: MIT License
Classifier: Operating System :: OS Independent
